[
    {
        "key": "dbln",
        "value": "%7B%2261556119441313%22%3A%22llAs7ju9%22%2C%2261555856253378%22%3A%22DXR38GZ8%22%2C%2261556336489968%22%3A%2269pazGmM%22%2C%2261556960400729%22%3A%22WfJgRK88%22%2C%2261556779605433%22%3A%22lcNFMJFA%22%2C%22100082377980115%22%3A%22lmtNOej8%22%2C%2261555963213963%22%3A%22VDwF6iGq%22%7D",
        "domain": "facebook.com",
        "path": "/login/device-based/",
        "hostOnly": false,
        "creation": "2024-04-07T02:15:52.486Z",
        "lastAccessed": "2024-04-07T02:15:52.486Z"
    },
    {
        "key": "sb",
        "value": "Q-m6ZdbtSrfXW_kHWEVGxgo3",
        "domain": "facebook.com",
        "path": "/",
        "hostOnly": false,
        "creation": "2024-04-07T02:15:52.486Z",
        "lastAccessed": "2024-04-07T02:15:52.486Z"
    },
    {
        "key": "datr",
        "value": "01gRZrkUsIzhDwsTJ61F3htx",
        "domain": "facebook.com",
        "path": "/",
        "hostOnly": false,
        "creation": "2024-04-07T02:15:52.486Z",
        "lastAccessed": "2024-04-07T02:15:52.486Z"
    },
    {
        "key": "ps_l",
        "value": "0",
        "domain": "facebook.com",
        "path": "/",
        "hostOnly": false,
        "creation": "2024-04-07T02:15:52.486Z",
        "lastAccessed": "2024-04-07T02:15:52.486Z"
    },
    {
        "key": "ps_n",
        "value": "0",
        "domain": "facebook.com",
        "path": "/",
        "hostOnly": false,
        "creation": "2024-04-07T02:15:52.486Z",
        "lastAccessed": "2024-04-07T02:15:52.486Z"
    },
    {
        "key": "wd",
        "value": "360x630",
        "domain": "facebook.com",
        "path": "/",
        "hostOnly": false,
        "creation": "2024-04-07T02:15:52.486Z",
        "lastAccessed": "2024-04-07T02:15:52.486Z"
    },
    {
        "key": "fr",
        "value": "0uOr4AIyzUcacGuhb.AWWDADYmKTsGGKBIKXu6DYY7dWg.BmEVjT..AAA.0.0.BmEgHA.AWWeOw09PwE",
        "domain": "facebook.com",
        "path": "/",
        "hostOnly": false,
        "creation": "2024-04-07T02:15:52.486Z",
        "lastAccessed": "2024-04-07T02:15:52.486Z"
    },
    {
        "key": "c_user",
        "value": "61556336489968",
        "domain": "facebook.com",
        "path": "/",
        "hostOnly": false,
        "creation": "2024-04-07T02:15:52.486Z",
        "lastAccessed": "2024-04-07T02:15:52.486Z"
    },
    {
        "key": "xs",
        "value": "30%3AodPknTfLtR98pA%3A2%3A1712456129%3A-1%3A13457",
        "domain": "facebook.com",
        "path": "/",
        "hostOnly": false,
        "creation": "2024-04-07T02:15:52.486Z",
        "lastAccessed": "2024-04-07T02:15:52.486Z"
    },
    {
        "key": "m_page_voice",
        "value": "61556336489968",
        "domain": "facebook.com",
        "path": "/",
        "hostOnly": false,
        "creation": "2024-04-07T02:15:52.486Z",
        "lastAccessed": "2024-04-07T02:15:52.486Z"
    },
    {
        "key": "locale",
        "value": "en_US",
        "domain": "facebook.com",
        "path": "/",
        "hostOnly": false,
        "creation": "2024-04-07T02:15:52.486Z",
        "lastAccessed": "2024-04-07T02:15:52.486Z"
    },
    {
        "key": "vpd",
        "value": "v1%3B630x360x2",
        "domain": "facebook.com",
        "path": "/",
        "hostOnly": false,
        "creation": "2024-04-07T02:15:52.487Z",
        "lastAccessed": "2024-04-07T02:15:52.487Z"
    }
]
